[
  {
    "ContainingType": "QuanLyKho.ControllersAPI.QuanLyDinhMuc",
    "Method": "GetChiTiet",
    "RelativePath": "api/quanlydinhmuc/chi-tiet/{id}",
    "HttpMethod": "GET",
    "IsController": true,
    "Order": 0,
    "Parameters": [
      {
        "Name": "id",
        "Type": "System.Int32",
        "IsRequired": true
      }
    ],
    "ReturnTypes": []
  },
  {
    "ContainingType": "QuanLyKho.ControllersAPI.QuanLyDinhMuc",
    "Method": "GetDanhSachDinhMuc",
    "RelativePath": "api/quanlydinhmuc/danhsachdinhmuc",
    "HttpMethod": "GET",
    "IsController": true,
    "Order": 0,
    "Parameters": [
      {
        "Name": "maLoaiXe",
        "Type": "System.Nullable\u00601[[System.Int32, System.Private.CoreLib, Version=8.0.0.0, Culture=neutral, PublicKeyToken=7cec85d7bea7798e]]",
        "IsRequired": false
      },
      {
        "Name": "page",
        "Type": "System.Int32",
        "IsRequired": false
      }
    ],
    "ReturnTypes": []
  },
  {
    "ContainingType": "QuanLyKho.ControllersAPI.QuanLyDinhMuc",
    "Method": "SuaDinhMuc",
    "RelativePath": "api/quanlydinhmuc/sua-dinh-muc/{id}",
    "HttpMethod": "PUT",
    "IsController": true,
    "Order": 0,
    "Parameters": [
      {
        "Name": "id",
        "Type": "System.Int32",
        "IsRequired": true
      },
      {
        "Name": "model",
        "Type": "QuanLyKho.Models.DinhMucBaoTri",
        "IsRequired": true
      }
    ],
    "ReturnTypes": []
  },
  {
    "ContainingType": "QuanLyKho.ControllersAPI.QuanLyDinhMuc",
    "Method": "ThemDinhMuc",
    "RelativePath": "api/quanlydinhmuc/them-dinh-muc",
    "HttpMethod": "POST",
    "IsController": true,
    "Order": 0,
    "Parameters": [
      {
        "Name": "model",
        "Type": "QuanLyKho.Models.DinhMucBaoTri",
        "IsRequired": true
      }
    ],
    "ReturnTypes": []
  },
  {
    "ContainingType": "QuanLyKho.ControllersAPI.QuanLyKho",
    "Method": "GetChiTietKhoBai",
    "RelativePath": "api/quanlykhobai/chitietkhobai/{maKho}",
    "HttpMethod": "GET",
    "IsController": true,
    "Order": 0,
    "Parameters": [
      {
        "Name": "maKho",
        "Type": "System.Int32",
        "IsRequired": true
      }
    ],
    "ReturnTypes": []
  },
  {
    "ContainingType": "QuanLyKho.ControllersAPI.QuanLyKho",
    "Method": "danhSachTen",
    "RelativePath": "api/quanlykhobai/danhsachtenkho",
    "HttpMethod": "GET",
    "IsController": true,
    "Order": 0,
    "Parameters": [],
    "ReturnTypes": []
  },
  {
    "ContainingType": "QuanLyKho.ControllersAPI.QuanLyKho",
    "Method": "GetAllKhoBai",
    "RelativePath": "api/quanlykhobai/getallkho",
    "HttpMethod": "GET",
    "IsController": true,
    "Order": 0,
    "Parameters": [
      {
        "Name": "seach",
        "Type": "System.String",
        "IsRequired": false
      },
      {
        "Name": "page",
        "Type": "System.Int32",
        "IsRequired": false
      },
      {
        "Name": "trangthai",
        "Type": "System.String",
        "IsRequired": false
      },
      {
        "Name": "loaikho",
        "Type": "System.String",
        "IsRequired": false
      }
    ],
    "ReturnTypes": []
  },
  {
    "ContainingType": "QuanLyKho.ControllersAPI.QuanLyKho",
    "Method": "GetAllLoaiKho",
    "RelativePath": "api/quanlykhobai/getallloaikho",
    "HttpMethod": "GET",
    "IsController": true,
    "Order": 0,
    "Parameters": [],
    "ReturnTypes": []
  },
  {
    "ContainingType": "QuanLyKho.ControllersAPI.QuanLyKho",
    "Method": "GetTenKhoBai",
    "RelativePath": "api/quanlykhobai/gettenkhobai",
    "HttpMethod": "GET",
    "IsController": true,
    "Order": 0,
    "Parameters": [],
    "ReturnTypes": []
  },
  {
    "ContainingType": "QuanLyKho.ControllersAPI.QuanLyKho",
    "Method": "ThemKhoMoi",
    "RelativePath": "api/quanlykhobai/themkhomoi",
    "HttpMethod": "POST",
    "IsController": true,
    "Order": 0,
    "Parameters": [
      {
        "Name": "newKho",
        "Type": "QuanLyKho.Models1.QuanLyKho.KhoBaiModels",
        "IsRequired": true
      }
    ],
    "ReturnTypes": []
  },
  {
    "ContainingType": "QuanLyKho.ControllersAPI.QuanLyKho",
    "Method": "ThemLoaiKhoMoi",
    "RelativePath": "api/quanlykhobai/themloaikhomoi",
    "HttpMethod": "POST",
    "IsController": true,
    "Order": 0,
    "Parameters": [
      {
        "Name": "newLoaiKho",
        "Type": "QuanLyKho.Models1.QuanLyKho.LoaiKhoModels",
        "IsRequired": true
      }
    ],
    "ReturnTypes": []
  },
  {
    "ContainingType": "QuanLyKho.ControllersAPI.QuanLyDanhXe",
    "Method": "CapNhatDangKiem",
    "RelativePath": "api/quanlyxe/capnhatdangkiem/{id}",
    "HttpMethod": "PUT",
    "IsController": true,
    "Order": 0,
    "Parameters": [
      {
        "Name": "id",
        "Type": "System.Int32",
        "IsRequired": true
      },
      {
        "Name": "IdDangKiem",
        "Type": "System.Int32",
        "IsRequired": false
      },
      {
        "Name": "MaPhuongTien",
        "Type": "System.Int32",
        "IsRequired": false
      },
      {
        "Name": "SoSeriGiayPhep",
        "Type": "System.String",
        "IsRequired": false
      },
      {
        "Name": "SoTemKiemDinh",
        "Type": "System.String",
        "IsRequired": false
      },
      {
        "Name": "NgayKiemDinh",
        "Type": "System.DateOnly",
        "IsRequired": false
      },
      {
        "Name": "NgayHetHan",
        "Type": "System.DateOnly",
        "IsRequired": false
      },
      {
        "Name": "DonViKiemDinh",
        "Type": "System.String",
        "IsRequired": false
      },
      {
        "Name": "PhiDuongBoDenNgay",
        "Type": "System.Nullable\u00601[[System.DateOnly, System.Private.CoreLib, Version=8.0.0.0, Culture=neutral, PublicKeyToken=7cec85d7bea7798e]]",
        "IsRequired": false
      },
      {
        "Name": "GhiChu",
        "Type": "System.String",
        "IsRequired": false
      },
      {
        "Name": "NgayTao",
        "Type": "System.Nullable\u00601[[System.DateTime, System.Private.CoreLib, Version=8.0.0.0, Culture=neutral, PublicKeyToken=7cec85d7bea7798e]]",
        "IsRequired": false
      },
      {
        "Name": "HinhAnhDangKiem",
        "Type": "System.String",
        "IsRequired": false
      },
      {
        "Name": "hinhAnh",
        "Type": "Microsoft.AspNetCore.Http.IFormFile",
        "IsRequired": false
      }
    ],
    "ReturnTypes": []
  },
  {
    "ContainingType": "QuanLyKho.ControllersAPI.QuanLyDanhXe",
    "Method": "CapNhatXe",
    "RelativePath": "api/quanlyxe/capnhatxe/{maPhuongTien}",
    "HttpMethod": "PUT",
    "IsController": true,
    "Order": 0,
    "Parameters": [
      {
        "Name": "maPhuongTien",
        "Type": "System.Int32",
        "IsRequired": true
      },
      {
        "Name": "model",
        "Type": "QuanLyKho.Models1.QuanLyXe.PhuongTienModels",
        "IsRequired": true
      }
    ],
    "ReturnTypes": []
  },
  {
    "ContainingType": "QuanLyKho.ControllersAPI.QuanLyDanhXe",
    "Method": "GetChiTietXe",
    "RelativePath": "api/quanlyxe/chitietphuongtien/{maPhuongTien}",
    "HttpMethod": "GET",
    "IsController": true,
    "Order": 0,
    "Parameters": [
      {
        "Name": "maPhuongTien",
        "Type": "System.Int32",
        "IsRequired": true
      }
    ],
    "ReturnTypes": []
  },
  {
    "ContainingType": "QuanLyKho.ControllersAPI.QuanLyDanhXe",
    "Method": "GetDanhSachLoaiXe",
    "RelativePath": "api/quanlyxe/danhsachloaixe",
    "HttpMethod": "GET",
    "IsController": true,
    "Order": 0,
    "Parameters": [
      {
        "Name": "searchTerm",
        "Type": "System.String",
        "IsRequired": false
      },
      {
        "Name": "page",
        "Type": "System.Int32",
        "IsRequired": false
      }
    ],
    "ReturnTypes": []
  },
  {
    "ContainingType": "QuanLyKho.ControllersAPI.QuanLyDanhXe",
    "Method": "GetDanhSachXe",
    "RelativePath": "api/quanlyxe/danhsachxe",
    "HttpMethod": "GET",
    "IsController": true,
    "Order": 0,
    "Parameters": [
      {
        "Name": "seaechTerm",
        "Type": "System.String",
        "IsRequired": false
      },
      {
        "Name": "page",
        "Type": "System.Int32",
        "IsRequired": false
      },
      {
        "Name": "maLoaiXe",
        "Type": "System.Nullable\u00601[[System.Int32, System.Private.CoreLib, Version=8.0.0.0, Culture=neutral, PublicKeyToken=7cec85d7bea7798e]]",
        "IsRequired": false
      },
      {
        "Name": "status",
        "Type": "System.String",
        "IsRequired": false
      },
      {
        "Name": "trangthaidangkiem",
        "Type": "System.String",
        "IsRequired": false
      }
    ],
    "ReturnTypes": []
  },
  {
    "ContainingType": "QuanLyKho.ControllersAPI.QuanLyDanhXe",
    "Method": "ExportBaoCaoXe",
    "RelativePath": "api/quanlyxe/export-bao-cao-xe",
    "HttpMethod": "GET",
    "IsController": true,
    "Order": 0,
    "Parameters": [
      {
        "Name": "loaiBaoCao",
        "Type": "System.String",
        "IsRequired": false
      },
      {
        "Name": "soNgayCanhBao",
        "Type": "System.Int32",
        "IsRequired": false
      }
    ],
    "ReturnTypes": []
  },
  {
    "ContainingType": "QuanLyKho.ControllersAPI.QuanLyDanhXe",
    "Method": "ThemLoaiXe",
    "RelativePath": "api/quanlyxe/themloaixe",
    "HttpMethod": "POST",
    "IsController": true,
    "Order": 0,
    "Parameters": [
      {
        "Name": "model",
        "Type": "QuanLyKho.Models1.QuanLyXe.LoaiXeModels",
        "IsRequired": true
      }
    ],
    "ReturnTypes": []
  },
  {
    "ContainingType": "QuanLyKho.ControllersAPI.QuanLyDanhXe",
    "Method": "ThemXe",
    "RelativePath": "api/quanlyxe/themxemoi",
    "HttpMethod": "POST",
    "IsController": true,
    "Order": 0,
    "Parameters": [
      {
        "Name": "model",
        "Type": "QuanLyKho.Models1.QuanLyXe.PhuongTienModels",
        "IsRequired": true
      }
    ],
    "ReturnTypes": []
  },
  {
    "ContainingType": "QuanLyKho.ControllersAPI.QuanLyDanhXe",
    "Method": "GetXeSapDenHanBaoTri",
    "RelativePath": "api/quanlyxe/xe-sap-den-han-bao-tri",
    "HttpMethod": "GET",
    "IsController": true,
    "Order": 0,
    "Parameters": [
      {
        "Name": "soNgayCanhBao",
        "Type": "System.Int32",
        "IsRequired": false
      },
      {
        "Name": "page",
        "Type": "System.Int32",
        "IsRequired": false
      },
      {
        "Name": "pageSize",
        "Type": "System.Int32",
        "IsRequired": false
      }
    ],
    "ReturnTypes": []
  },
  {
    "ContainingType": "QuanLyKho.ControllersAPI.QuanLyDanhXe",
    "Method": "GetXeHetHanDangKiem",
    "RelativePath": "api/quanlyxe/xe-sap-het-han-dang-kiem",
    "HttpMethod": "GET",
    "IsController": true,
    "Order": 0,
    "Parameters": [
      {
        "Name": "soNgayCanhBao",
        "Type": "System.Int32",
        "IsRequired": false
      },
      {
        "Name": "page",
        "Type": "System.Int32",
        "IsRequired": false
      },
      {
        "Name": "pageSize",
        "Type": "System.Int32",
        "IsRequired": false
      }
    ],
    "ReturnTypes": []
  },
  {
    "ContainingType": "QuanLyKho.ControllersAPI.QuanLyDanhXe",
    "Method": "GetXeSapHetHanPhiDuongBo",
    "RelativePath": "api/quanlyxe/xe-sap-het-han-phi-duong-bo",
    "HttpMethod": "GET",
    "IsController": true,
    "Order": 0,
    "Parameters": [
      {
        "Name": "soNgayCanhBao",
        "Type": "System.Int32",
        "IsRequired": false
      },
      {
        "Name": "page",
        "Type": "System.Int32",
        "IsRequired": false
      },
      {
        "Name": "pageSize",
        "Type": "System.Int32",
        "IsRequired": false
      }
    ],
    "ReturnTypes": []
  },
  {
    "ContainingType": "QuanLyKho.Controllers.WeatherForecastController",
    "Method": "Get",
    "RelativePath": "WeatherForecast",
    "HttpMethod": "GET",
    "IsController": true,
    "Order": 0,
    "Parameters": [],
    "ReturnTypes": [
      {
        "Type": "System.Collections.Generic.IEnumerable\u00601[[QuanLyKho.WeatherForecast, QuanLyKho, Version=1.0.0.0, Culture=neutral, PublicKeyToken=null]]",
        "MediaTypes": [
          "text/plain",
          "application/json",
          "text/json"
        ],
        "StatusCode": 200
      }
    ],
    "EndpointName": "GetWeatherForecast"
  }
]